houflask/__init__.py
houflask/cache.py
houflask/connexion.py
houflask/error_handler.py
houflask/exceptions.py
houflask/http.py
houflask/py.typed
houflask/rapidjson.py
houflask/auth/__init__.py
houflask/auth/swagger-spec.yml
houflask/auth/daos/__init__.py
houflask/auth/daos/account_dao.py
houflask/auth/daos/authentication_dao.py
houflask/auth/daos/permission_dao.py
houflask/auth/services/__init__.py
houflask/auth/services/authentication_service.py
houflask/auth/services/authorization_service.py
houflask/auth/views/__init__.py
houflask/auth/views/authentication_view.py
houflask/feature_flag/__init__.py
houflask/feature_flag/swagger-spec.yml
houflask/feature_flag/daos/__init__.py
houflask/feature_flag/daos/feature_flag_dao.py
houflask/feature_flag/services/__init__.py
houflask/feature_flag/services/feature_flag_service.py
houflask/feature_flag/views/__init__.py
houflask/feature_flag/views/feature_flag.py
houflask/meta/__init__.py
houflask/meta/swagger-spec.yml
houflask/meta/views/__init__.py
houflask/meta/views/meta.py
houflask/organization/__init__.py
houflask/organization/swagger-spec.yml
houflask/organization/daos/__init__.py
houflask/organization/daos/organization_account_dao.py
houflask/organization/daos/organization_dao.py
houflask/organization/services/__init__.py
houflask/organization/services/organization_account_service.py
houflask/organization/services/organization_service.py
houflask/organization/views/__init__.py
houflask/organization/views/organization.py
houflask/test_utils/__init__.py
houflask/test_utils/base_factory.py
houflask/test_utils/functional_base.py
tests/__init__.py
tests/functional/__init__.py
tests/functional/account_test.py
tests/functional/authentication_test.py
tests/functional/feature_flag_test.py
tests/functional/meta_test.py
tests/functional/organization_test.py
tests/integration/__init__.py
tests/integration/auth/__init__.py
tests/integration/auth/daos/__init__.py
tests/integration/auth/daos/account_dao_test.py
hou_flask-0.0.14.dist-info/METADATA
hou_flask-0.0.14.dist-info/WHEEL
hou_flask-0.0.14.dist-info/top_level.txt
hou_flask-0.0.14.dist-info/RECORD
