Metadata-Version: 2.1
Name: hou-flask
Version: 0.0.14
Summary: Basic authentication and authorization application
Home-page: https://github.com/timmartin19/hou-flask
Author: Tim Martin
Author-email: oss@timmartin.me
License: UNKNOWN
Keywords: houflask
Platform: UNKNOWN
Classifier: Development Status :: 2 - Pre-Alpha
Classifier: Intended Audience :: Developers
Classifier: Natural Language :: English
Classifier: Programming Language :: Python :: 3.5
Classifier: Programming Language :: Python :: 3.6
Classifier: Programming Language :: Python :: 3.7
Classifier: Programming Language :: Python :: 3.8
Requires-Dist: hou-flask-psycopg2
Requires-Dist: python-rapidjson
Requires-Dist: flask
Requires-Dist: connexion (>=2.7.0)
Requires-Dist: werkzeug
Requires-Dist: ultra-config
Requires-Dist: jsonschema (>=3.0.0)
Requires-Dist: beaker
Requires-Dist: boto3
Requires-Dist: python-jose
Requires-Dist: flask-wtf
Requires-Dist: pystatuschecker
Requires-Dist: factory-boy
Requires-Dist: flask-webtest
